LICENSE
MANIFEST.in
README.md
setup.py
trasso/__init__.py
trasso/__version__.py
trasso/core.py
trasso.egg-info/PKG-INFO
trasso.egg-info/SOURCES.txt
trasso.egg-info/dependency_links.txt
trasso.egg-info/top_level.txt