Metadata-Version: 2.1
Name: trasso
Version: 5.3.1
Summary: Extract association words using TextRank.
Home-page: https://github.com/HankTown/trasso
Author: HankTown
License: MIT
Platform: UNKNOWN
Classifier: License :: OSI Approved :: MIT License
Classifier: Programming Language :: Python
Classifier: Programming Language :: Python :: 3
Classifier: Programming Language :: Python :: 3.6
Classifier: Programming Language :: Python :: Implementation :: CPython
Classifier: Programming Language :: Python :: Implementation :: PyPy
Requires-Python: >=3.6.0
